README.md
setup.py
docker_parse/__init__.py
docker_parse.egg-info/PKG-INFO
docker_parse.egg-info/SOURCES.txt
docker_parse.egg-info/dependency_links.txt
docker_parse.egg-info/entry_points.txt
docker_parse.egg-info/requires.txt
docker_parse.egg-info/top_level.txt