Metadata-Version: 1.1
Name: docker-parse
Version: 0.5.6
Summary: Parse docker-run options from a running Docker container
Home-page: https://github.com/iamfat/docker-parse
Author: Jia Huang
Author-email: iamfat@gmail.com
License: MIT
Keywords: docker parse run options
Platform: UNKNOWN
Classifier: Development Status :: 4 - Beta
Classifier: Intended Audience :: Developers
Classifier: Topic :: Utilities
Classifier: License :: OSI Approved :: MIT License
